etcd/__init__.py
async_etcd-0.0.0.dist-info/LICENSE
async_etcd-0.0.0.dist-info/WHEEL
async_etcd-0.0.0.dist-info/METADATA
async_etcd-0.0.0.dist-info/RECORD
